src/__init__.py
src/aurai.py
RevAuraArtificial_intaligenceai-0.1.0.dist-info/METADATA
RevAuraArtificial_intaligenceai-0.1.0.dist-info/WHEEL
RevAuraArtificial_intaligenceai-0.1.0.dist-info/top_level.txt
RevAuraArtificial_intaligenceai-0.1.0.dist-info/RECORD
