Metadata-Version: 2.1
Name: RevAuraArtificial-intaligenceai
Version: 0.1.0
Summary: aithis is a
Author: code sx
Author-email: core@ex.com
Requires-Dist: requests
